{
    "patches": [
        {
            "label": "2026-04-11_22-01-24",
            "content": "@@ -41,93 +41,35 @@\n     \n-var a ,b int%0A    fmt.Scan(&a,&b)%0A    for i:=a; i%3C=b; i++%7B%0A    fmt.Println(i)%0A    %7D%0A   \n+fmt.Println(%22Hello, World!%22)\n %0A%7D%0A\n",
            "lines": "5"
        },
        {
            "label": "2026-04-11_22-07-47",
            "content": "@@ -112,15 +112,11 @@\n rint\n-f(%22%25d%22,\n+ln(\n i)%0A \n",
            "lines": "10"
        },
        {
            "label": "2026-04-11_22-08-17",
            "content": "@@ -115,17 +115,16 @@\n tf(%22%25d%22,\n- \n i)%0A    %7D\n",
            "lines": "10"
        },
        {
            "label": "2026-04-11_22-08-26",
            "content": "@@ -114,17 +114,16 @@\n ntf(%22%25d%22\n- \n , i)%0A   \n",
            "lines": "10"
        },
        {
            "label": "2026-04-11_22-08-38",
            "content": "@@ -74,27 +74,8 @@\n &b)%0A\n-    fmt.Print(%22%5B%22)%0A\n     \n@@ -116,16 +116,17 @@\n f(%22%25d%22 ,\n+ \n i)%0A    %7D\n@@ -133,21 +133,7 @@\n %0A   \n-fmt.Print(%22%5D%22)\n %0A%7D%0A\n",
            "lines": "10"
        },
        {
            "label": "2026-04-11_22-09-32",
            "content": "@@ -86,17 +86,16 @@\n Print(%22%5B\n- \n %22)%0A    f\n@@ -158,15 +158,14 @@\n .Print(%22\n- \n %5D%22)%0A%7D%0A\n",
            "lines": "11"
        },
        {
            "label": "2026-04-11_22-09-41",
            "content": "@@ -6,17 +6,16 @@\n ge main%0A\n-%0A\n import %22\n@@ -19,17 +19,16 @@\n t %22fmt%22%0A\n-%0A\n func mai\n@@ -37,23 +37,29 @@\n ) %7B%0A\n-%09\n+    \n var a\n-,\n  \n+,\n b int%0A\n-%09\n+    \n fmt.\n@@ -70,14 +70,16 @@\n (&a,\n- \n &b)%0A\n-%09\n+    \n fmt.\n@@ -94,37 +94,37 @@\n  %22)%0A\n-%09\n+    \n for i\n- \n :=\n- \n a; i\n- \n %3C=\n- \n b; i++\n- \n %7B%0A\n-%09%09\n+    \n fmt.\n@@ -138,55 +138,22 @@\n %22%25d%22\n-,\n  \n+,\n i)%0A\n-%09%09if i %3E b+1 %7B%0A%09%09%09fmt.Print(%22 %22)%0A%0A%09%09%7D%0A%09%7D%0A%09\n+    %7D%0A   \n fmt.\n",
            "lines": "11"
        },
        {
            "label": "2026-04-11_22-10-46",
            "content": "@@ -140,17 +140,17 @@\n %0A%09%09if i \n-%3C\n+%3E\n  b+1 %7B%0A%09\n",
            "lines": "17"
        },
        {
            "label": "2026-04-11_22-11-12",
            "content": "@@ -147,9 +147,9 @@\n  %3C b\n--\n++\n 1 %7B%0A\n",
            "lines": "17"
        },
        {
            "label": "2026-04-11_22-12-01",
            "content": "@@ -143,16 +143,18 @@\n if i %3C b\n+-1\n  %7B%0A%09%09%09fm\n",
            "lines": "17"
        },
        {
            "label": "2026-04-11_22-12-14",
            "content": "@@ -100,16 +100,17 @@\n = a; i %3C\n+=\n  b; i++ \n",
            "lines": "17"
        },
        {
            "label": "2026-04-11_22-12-42",
            "content": "@@ -183,14 +183,15 @@\n .Print(%22\n+ \n %5D%22)%0A%7D%0A\n",
            "lines": "17"
        },
        {
            "label": "2026-04-11_22-12-53",
            "content": "@@ -146,10 +146,9 @@\n  %3C b\n--1\n+ \n %7B%0A%09%09\n@@ -163,16 +163,17 @@\n nt(%22 %22)%0A\n+%0A\n %09%09%7D%0A%09%7D%0A%09\n@@ -183,15 +183,14 @@\n .Print(%22\n- \n %5D%22)%0A%7D%0A\n",
            "lines": "17"
        },
        {
            "label": "2026-04-11_22-15-58",
            "content": "@@ -183,14 +183,15 @@\n .Print(%22\n+ \n %5D%22)%0A%7D%0A\n",
            "lines": "16"
        },
        {
            "label": "2026-04-11_22-16-33",
            "content": "@@ -183,15 +183,14 @@\n .Print(%22\n- \n %5D%22)%0A%7D%0A\n",
            "lines": "16"
        },
        {
            "label": "2026-04-11_22-16-42",
            "content": "@@ -142,16 +142,18 @@\n if i %3C b\n+-1\n %7B%0A%09%09%09fmt\n",
            "lines": "16"
        },
        {
            "label": "2026-04-11_22-16-58",
            "content": "@@ -181,14 +181,15 @@\n .Print(%22\n+ \n %5D%22)%0A%7D%0A\n",
            "lines": "16"
        },
        {
            "label": "2026-04-11_22-17-04",
            "content": "@@ -142,17 +142,16 @@\n if i %3C b\n- \n %7B%0A%09%09%09fmt\n",
            "lines": "16"
        },
        {
            "label": "2026-04-11_22-17-25",
            "content": "@@ -182,15 +182,14 @@\n .Print(%22\n- \n %5D%22)%0A%7D%0A\n",
            "lines": "16"
        },
        {
            "label": "2026-04-11_22-18-21",
            "content": "@@ -182,14 +182,15 @@\n .Print(%22\n+ \n %5D%22)%0A%7D%0A\n",
            "lines": "16"
        },
        {
            "label": "2026-04-11_22-18-28",
            "content": "@@ -183,14 +183,13 @@\n Print(%22%5D\n- \n %22)%0A%7D%0A\n",
            "lines": "16"
        },
        {
            "label": "2026-04-11_22-19-13",
            "content": "@@ -187,10 +187,9 @@\n t(%22%5D\n-%5Cn\n+ \n %22)%0A%7D\n",
            "lines": "16"
        },
        {
            "label": "2026-04-11_22-19-28",
            "content": "@@ -77,18 +77,16 @@\n mt.Print\n-ln\n (%22%5B %22)%0A%09\n@@ -184,13 +184,13 @@\n rint\n-ln\n (%22%5D\n+%5Cn\n %22)%0A%7D\n",
            "lines": "16"
        },
        {
            "label": "2026-04-11_22-20-34",
            "content": "@@ -77,16 +77,18 @@\n mt.Print\n+ln\n (%22%5B %22)%0A%09\n",
            "lines": "16"
        },
        {
            "label": "2026-04-11_22-20-44",
            "content": "package main\n\nimport \"fmt\"\n\nfunc main() {\n\tvar a, b int\n\tfmt.Scan(&a, &b)\n\tfmt.Print(\"[ \")\n\tfor i := a; i < b; i++ {\n\t\tfmt.Printf(\"%d\", i)\n\t\tif i < b {\n\t\t\tfmt.Print(\" \")\n\t\t}\n\t}\n\tfmt.Println(\"]\")\n}\n",
            "lines": "16"
        }
    ]
}